aioprometheus/__init__.py
aioprometheus/collectors.py
aioprometheus/decorators.py
aioprometheus/histogram.py
aioprometheus/metricdict.py
aioprometheus/mypy_types.py
aioprometheus/negotiator.py
aioprometheus/process.py
aioprometheus/pusher.py
aioprometheus/py.typed
aioprometheus/registry.py
aioprometheus/renderer.py
aioprometheus/service.py
aioprometheus/asgi/__init__.py
aioprometheus/asgi/middleware.py
aioprometheus/asgi/quart.py
aioprometheus/asgi/starlette.py
aioprometheus/formats/__init__.py
aioprometheus/formats/base.py
aioprometheus/formats/binary.py
aioprometheus/formats/mypy_types.py
aioprometheus/formats/text.py
aioprometheus-23.3.0.dist-info/METADATA
aioprometheus-23.3.0.dist-info/WHEEL
aioprometheus-23.3.0.dist-info/top_level.txt
aioprometheus-23.3.0.dist-info/RECORD
