Metadata-Version: 2.1
Name: aioprometheus
Version: 23.3.0
Summary: A Prometheus Python client library for asyncio-based applications
Home-page: https://github.com/claws/aioprometheus
Author: Chris Laws
Author-email: clawsicus@gmail.com
License: MIT
Keywords: prometheus,monitoring,metrics
Classifier: Development Status :: 5 - Production/Stable
Classifier: Intended Audience :: Developers
Classifier: License :: OSI Approved :: MIT License
Classifier: Programming Language :: Python
Classifier: Programming Language :: Python :: 3
Classifier: Programming Language :: Python :: 3.8
Classifier: Programming Language :: Python :: 3.9
Classifier: Programming Language :: Python :: 3.10
Classifier: Programming Language :: Python :: 3.11
Classifier: Topic :: Software Development :: Libraries :: Python Modules
Classifier: Topic :: System :: Monitoring
Classifier: Typing :: Typed
Requires-Python: >=3.8.0
Requires-Dist: orjson
Requires-Dist: quantile-python (>=1.1)
Provides-Extra: aiohttp
Requires-Dist: aiohttp (>=3.3.2) ; extra == 'aiohttp'
Provides-Extra: quart
Requires-Dist: quart (>=0.15.1) ; extra == 'quart'
Provides-Extra: starlette
Requires-Dist: starlette (>=0.14.2) ; extra == 'starlette'
